[{"date": "2026-01-15T21:00:00", "surprise": 4.62, "estimate": 1.82, "actual": 1.9}, {"date": "2025-10-15T20:00:00", "surprise": 20.66, "estimate": 1.46, "actual": 1.76}, {"date": "2025-07-15T20:00:00", "surprise": 0.9, "estimate": 1.3, "actual": 1.31}, {"date": "2025-04-15T20:00:00", "surprise": 2.19, "estimate": 1.14, "actual": 1.17}, {"date": "2025-01-16T21:00:00", "surprise": -5.83, "estimate": 1.62, "actual": 1.53}, {"date": "2024-10-15T20:00:00", "surprise": 7.21, "estimate": 1.39, "actual": 1.49}, {"date": "2024-07-16T20:00:00", "surprise": -10.78, "estimate": 1.48, "actual": 1.32}, {"date": "2024-04-16T20:00:00", "surprise": -19.3, "estimate": 1.51, "actual": 1.22}, {"date": "2024-01-18T21:00:00", "surprise": -15.54, "estimate": 1.74, "actual": 1.47}, {"date": "2023-10-17T20:00:00", "surprise": -1.72, "estimate": 1.83, "actual": 1.8}, {"date": "2023-07-18T20:00:00", "surprise": -4.89, "estimate": 1.9, "actual": 1.81}, {"date": "2023-04-17T20:00:00", "surprise": -6.16, "estimate": 2.01, "actual": 1.89}, {"date": "2023-01-18T12:00:00", "surprise": -21.4, "estimate": 2.44, "actual": 1.92}, {"date": "2022-10-18T20:00:00", "surprise": 4.62, "estimate": 2.46, "actual": 2.57}, {"date": "2022-07-19T20:00:00", "surprise": 2.81, "estimate": 2.35, "actual": 2.42}, {"date": "2022-04-18T20:00:00", "surprise": 18.32, "estimate": 1.94, "actual": 2.29}, {"date": "2022-01-18T21:00:00", "surprise": 13.07, "estimate": 2.02, "actual": 2.28}, {"date": "2021-10-15T11:00:00", "surprise": 5.7, "estimate": 1.78, "actual": 1.88}, {"date": "2021-07-19T20:00:00", "surprise": 2.38, "estimate": 1.57, "actual": 1.61}, {"date": "2021-04-15T20:00:00", "surprise": 17.45, "estimate": 1.17, "actual": 1.37}, {"date": "2021-01-19T21:00:00", "surprise": 10.22, "estimate": 1.31, "actual": 1.44}, {"date": "2020-10-16T11:00:00", "surprise": -8.5, "estimate": 1.29, "actual": 1.18}, {"date": "2020-07-16T20:00:00", "surprise": 34.38, "estimate": 0.85, "actual": 1.14}, {"date": "2020-04-14T21:00:00", "surprise": 0.5, "estimate": 0.98, "actual": 0.98}, {"date": "2020-01-17T12:00:00", "surprise": -10.65, "estimate": 1.51, "actual": 1.35}, {"date": "2019-10-15T20:00:00", "surprise": -3.18, "estimate": 1.45, "actual": 1.4}, {"date": "2019-07-15T20:00:00", "surprise": 1.75, "estimate": 1.35, "actual": 1.37}, {"date": "2019-04-15T20:00:00", "surprise": -12.64, "estimate": 1.25, "actual": 1.09}, {"date": "2019-01-17T21:00:00", "surprise": 19.92, "estimate": 1.48, "actual": 1.78}, {"date": "2018-10-15T20:00:00", "surprise": 5.89, "estimate": 1.39, "actual": 1.47}, {"date": "2018-07-16T11:00:00", "surprise": 7.0, "estimate": 1.28, "actual": 1.37}, {"date": "2018-04-16T09:00:00", "surprise": 1.26, "estimate": 1.06, "actual": 1.07}, {"date": "2018-01-18T12:00:00", "surprise": -13.53, "estimate": 1.02, "actual": 0.88}, {"date": "2017-10-13T11:00:00", "surprise": -5.65, "estimate": 0.96, "actual": 0.91}, {"date": "2017-07-17T11:00:00", "surprise": -3.58, "estimate": 0.91, "actual": 0.88}, {"date": "2017-04-17T11:00:00", "surprise": -5.76, "estimate": 0.85, "actual": 0.8}, {"date": "2017-01-19T12:00:00", "surprise": -3.82, "estimate": 1.01, "actual": 0.97}, {"date": "2016-10-17T11:00:00", "surprise": -4.98, "estimate": 1.02, "actual": 0.97}, {"date": "2016-07-18T11:00:00", "surprise": -5.82, "estimate": 0.98, "actual": 0.92}, {"date": "2016-04-18T11:00:00", "surprise": 3.22, "estimate": 0.85, "actual": 0.88}, {"date": "2016-01-21T12:00:00", "surprise": 1.79, "estimate": 0.99, "actual": 1.01}, {"date": "2015-10-14T11:00:00", "surprise": 1.76, "estimate": 0.97, "actual": 0.99}, {"date": "2015-07-17T12:00:00", "surprise": -2.42, "estimate": 0.9, "actual": 0.88}, {"date": "2015-04-14T12:00:00", "surprise": 8.15, "estimate": 0.72, "actual": 0.78}, {"date": "2015-01-22T13:00:00", "surprise": 5.17, "estimate": 0.88, "actual": 0.93}, {"date": "2014-10-14T12:00:00", "surprise": 3.1, "estimate": 0.84, "actual": 0.87}, {"date": "2014-07-15T12:00:00", "surprise": 0.53, "estimate": 0.79, "actual": 0.79}, {"date": "2014-04-14T12:00:00", "surprise": -5.15, "estimate": 0.61, "actual": 0.58}, {"date": "2014-01-23T13:00:00", "surprise": -2.85, "estimate": 0.79, "actual": 0.77}, {"date": "2013-10-15T12:00:00", "surprise": -4.06, "estimate": 0.78, "actual": 0.75}, {"date": "2013-07-15T12:00:00", "surprise": -1.81, "estimate": 0.74, "actual": 0.73}, {"date": "2013-04-11T20:00:00", "surprise": -5.19, "estimate": 0.64, "actual": 0.61}, {"date": "2013-01-24T13:00:00", "surprise": 0.9, "estimate": 0.69, "actual": 0.7}, {"date": "2012-10-11T20:00:00", "surprise": -1.99, "estimate": 0.66, "actual": 0.65}, {"date": "2012-07-16T20:00:00", "surprise": 1.02, "estimate": 0.66, "actual": 0.67}, {"date": "2012-04-12T20:00:00", "surprise": 10.82, "estimate": 0.51, "actual": 0.57}, {"date": "2012-01-26T21:00:00", "surprise": 8.19, "estimate": 0.58, "actual": 0.63}, {"date": "2011-10-13T20:00:00", "surprise": 1.56, "estimate": 0.56, "actual": 0.57}, {"date": "2011-07-14T20:00:00", "surprise": 1.0, "estimate": 0.52, "actual": 0.53}, {"date": "2011-04-13T20:00:00", "surprise": 5.22, "estimate": 0.38, "actual": 0.4}, {"date": "2011-01-28T14:00:00", "surprise": 3.23, "estimate": 0.45, "actual": 0.46}, {"date": "2010-10-14T20:00:00", "surprise": -2.49, "estimate": 0.44, "actual": 0.43}, {"date": "2010-07-15T20:00:00", "surprise": 12.7, "estimate": 0.35, "actual": 0.4}, {"date": "2010-04-14T19:00:00", "surprise": 8.94, "estimate": 0.27, "actual": 0.29}, {"date": "2010-01-27T22:00:00", "surprise": 0.35, "estimate": 0.32, "actual": 0.32}, {"date": "2009-10-19T20:00:00", "surprise": 9.84, "estimate": 0.28, "actual": 0.31}, {"date": "2009-07-14T20:00:00", "surprise": -24.66, "estimate": 0.31, "actual": 0.23}, {"date": "2009-04-13T20:00:00", "surprise": 7.57, "estimate": 0.22, "actual": 0.24}, {"date": "2009-01-29T13:00:00", "surprise": 8.52, "estimate": 0.4, "actual": 0.43}, {"date": "2008-10-14T12:00:00", "surprise": 12.02, "estimate": 0.42, "actual": 0.47}, {"date": "2008-07-14T20:00:00", "surprise": 9.2, "estimate": 0.36, "actual": 0.39}, {"date": "2008-04-14T20:00:00", "surprise": -8.16, "estimate": 0.3, "actual": 0.28}, {"date": "2008-01-29T21:00:00", "surprise": 17.97, "estimate": 0.39, "actual": 0.46}, {"date": "2007-10-11T20:00:00", "surprise": -4.15, "estimate": 0.4, "actual": 0.38}, {"date": "2007-07-16T20:00:00", "surprise": 0.62, "estimate": 0.38, "actual": 0.38}, {"date": "2007-04-16T19:00:00", "surprise": -1.23, "estimate": 0.3, "actual": 0.3}, {"date": "2007-01-29T15:00:00", "surprise": 9.18, "estimate": 0.4, "actual": 0.44}, {"date": "2006-10-13T12:00:00", "surprise": 4.84, "estimate": 0.37, "actual": 0.39}, {"date": "2006-07-18T12:00:00", "surprise": -2.7, "estimate": 0.37, "actual": 0.36}, {"date": "2006-04-17T12:00:00", "surprise": -0.5, "estimate": 0.31, "actual": 0.31}, {"date": "2006-01-30T12:00:00", "surprise": 13.57, "estimate": 0.36, "actual": 0.41}, {"date": "2005-10-14T12:00:00", "surprise": -0.19, "estimate": 0.35, "actual": 0.35}, {"date": "2005-07-15T11:00:00", "surprise": -8.6, "estimate": 0.36, "actual": 0.33}, {"date": "2005-04-14T20:00:00", "surprise": 11.79, "estimate": 0.25, "actual": 0.28}, {"date": "2005-02-02T21:00:00", "surprise": 11.5, "estimate": 0.29, "actual": 0.32}, {"date": "2004-10-15T12:00:00", "surprise": 4.4, "estimate": 0.27, "actual": 0.28}, {"date": "2004-07-15T22:00:00", "surprise": 18.53, "estimate": 0.23, "actual": 0.28}, {"date": "2004-04-14T12:00:00", "surprise": 50.0, "estimate": 0.12, "actual": 0.2}, {"date": "2004-01-28T14:00:00", "surprise": -7.51, "estimate": 0.17, "actual": 0.16}, {"date": "2003-10-14T12:00:00", "surprise": 25.0, "estimate": 0.16, "actual": 0.2}, {"date": "2003-07-15T11:00:00", "surprise": 30.25, "estimate": 0.12, "actual": 0.16}, {"date": "2003-04-14T21:00:00", "surprise": 50.0, "estimate": 0.04, "actual": 0.07}, {"date": "2003-01-30T13:00:00", "surprise": -8.82, "estimate": 0.1, "actual": 0.09}, {"date": "2002-10-15T11:00:00", "surprise": 15.38, "estimate": 0.09, "actual": 0.11}, {"date": "2002-07-15T08:00:00", "surprise": 50.0, "estimate": 0.07, "actual": 0.1}, {"date": "2002-04-15T12:00:00", "surprise": 26.92, "estimate": 0.03, "actual": 0.03}, {"date": "2002-01-30T14:00:00", "surprise": 50.0, "estimate": 0.04, "actual": 0.06}, {"date": "2001-10-15T13:00:00", "surprise": 50.0, "estimate": 0.01, "actual": 0.03}, {"date": "2001-07-16T21:00:00", "surprise": 50.0, "estimate": 0.04, "actual": 0.06}]