[{"date": "2026-03-10T20:00:00", "surprise": 5.69, "estimate": 1.69, "actual": 1.79}, {"date": "2025-12-10T21:00:00", "surprise": 38.04, "estimate": 1.64, "actual": 2.26}, {"date": "2025-09-09T20:00:00", "surprise": -0.62, "estimate": 1.48, "actual": 1.47}, {"date": "2025-06-11T20:00:00", "surprise": 3.37, "estimate": 1.64, "actual": 1.7}, {"date": "2025-03-10T20:00:00", "surprise": -4.1, "estimate": 1.06, "actual": 1.02}, {"date": "2024-12-09T21:00:00", "surprise": -0.77, "estimate": 1.48, "actual": 1.47}, {"date": "2024-09-09T20:00:00", "surprise": 4.29, "estimate": 1.33, "actual": 1.39}, {"date": "2024-06-11T20:00:00", "surprise": -1.14, "estimate": 1.65, "actual": 1.63}, {"date": "2024-03-11T20:00:00", "surprise": 2.47, "estimate": 1.38, "actual": 1.41}, {"date": "2023-12-11T21:00:00", "surprise": 0.95, "estimate": 1.33, "actual": 1.34}, {"date": "2023-09-11T20:00:00", "surprise": 3.46, "estimate": 1.15, "actual": 1.19}, {"date": "2023-06-12T20:00:00", "surprise": 5.56, "estimate": 1.58, "actual": 1.67}, {"date": "2023-03-09T21:00:00", "surprise": 1.44, "estimate": 1.2, "actual": 1.22}, {"date": "2022-12-12T21:00:00", "surprise": 3.15, "estimate": 1.17, "actual": 1.21}, {"date": "2022-09-12T20:00:00", "surprise": -4.22, "estimate": 1.08, "actual": 1.03}, {"date": "2022-06-13T20:00:00", "surprise": 11.95, "estimate": 1.38, "actual": 1.54}, {"date": "2022-03-10T21:00:00", "surprise": -4.02, "estimate": 1.18, "actual": 1.13}, {"date": "2021-12-09T21:00:00", "surprise": 8.53, "estimate": 1.11, "actual": 1.21}, {"date": "2021-09-13T20:00:00", "surprise": 6.4, "estimate": 0.97, "actual": 1.03}, {"date": "2021-06-15T20:00:00", "surprise": 15.62, "estimate": 1.33, "actual": 1.54}, {"date": "2021-03-10T21:00:00", "surprise": 4.54, "estimate": 1.11, "actual": 1.16}, {"date": "2020-12-10T21:00:00", "surprise": 6.13, "estimate": 1.0, "actual": 1.06}, {"date": "2020-09-10T20:00:00", "surprise": 7.77, "estimate": 0.86, "actual": 0.93}, {"date": "2020-06-16T20:00:00", "surprise": 4.16, "estimate": 1.15, "actual": 1.2}, {"date": "2020-03-12T20:00:00", "surprise": 1.06, "estimate": 0.96, "actual": 0.97}, {"date": "2019-12-12T21:00:00", "surprise": 1.51, "estimate": 0.89, "actual": 0.9}, {"date": "2019-09-11T20:00:00", "surprise": 0.24, "estimate": 0.81, "actual": 0.81}, {"date": "2019-06-19T20:00:00", "surprise": 7.98, "estimate": 1.07, "actual": 1.16}, {"date": "2019-03-14T20:00:00", "surprise": 3.41, "estimate": 0.84, "actual": 0.87}, {"date": "2018-12-17T21:00:00", "surprise": 2.36, "estimate": 0.78, "actual": 0.8}, {"date": "2018-09-17T20:00:00", "surprise": 3.75, "estimate": 0.68, "actual": 0.71}, {"date": "2018-06-19T20:00:00", "surprise": 5.14, "estimate": 0.94, "actual": 0.99}, {"date": "2018-03-19T20:00:00", "surprise": 14.81, "estimate": 0.72, "actual": 0.83}, {"date": "2017-12-14T21:00:00", "surprise": 2.67, "estimate": 0.68, "actual": 0.7}, {"date": "2017-09-14T20:00:00", "surprise": 2.68, "estimate": 0.6, "actual": 0.62}, {"date": "2017-06-21T20:00:00", "surprise": 13.58, "estimate": 0.78, "actual": 0.89}, {"date": "2017-03-15T20:00:00", "surprise": 11.75, "estimate": 0.62, "actual": 0.69}, {"date": "2016-12-15T21:00:00", "surprise": 1.74, "estimate": 0.6, "actual": 0.61}, {"date": "2016-09-15T20:00:00", "surprise": -5.06, "estimate": 0.58, "actual": 0.55}, {"date": "2016-06-16T20:00:00", "surprise": -0.68, "estimate": 0.82, "actual": 0.81}, {"date": "2016-03-15T20:00:00", "surprise": 3.25, "estimate": 0.62, "actual": 0.64}, {"date": "2015-12-16T21:00:00", "surprise": 4.98, "estimate": 0.6, "actual": 0.63}, {"date": "2015-09-16T20:00:00", "surprise": 1.31, "estimate": 0.52, "actual": 0.53}, {"date": "2015-06-17T20:00:00", "surprise": -9.79, "estimate": 0.86, "actual": 0.78}, {"date": "2015-03-17T20:00:00", "surprise": -0.22, "estimate": 0.68, "actual": 0.68}, {"date": "2014-12-17T21:00:00", "surprise": 1.05, "estimate": 0.68, "actual": 0.69}, {"date": "2014-09-18T20:00:00", "surprise": -2.91, "estimate": 0.64, "actual": 0.62}, {"date": "2014-06-19T20:00:00", "surprise": -3.64, "estimate": 0.95, "actual": 0.92}, {"date": "2014-03-18T20:00:00", "surprise": -2.95, "estimate": 0.7, "actual": 0.68}, {"date": "2013-12-18T21:00:00", "surprise": 2.63, "estimate": 0.67, "actual": 0.69}, {"date": "2013-09-18T20:00:00", "surprise": 5.12, "estimate": 0.56, "actual": 0.59}, {"date": "2013-06-20T20:00:00", "surprise": -0.66, "estimate": 0.88, "actual": 0.87}, {"date": "2013-03-20T20:00:00", "surprise": -1.9, "estimate": 0.66, "actual": 0.65}, {"date": "2012-12-18T21:00:00", "surprise": 5.05, "estimate": 0.61, "actual": 0.64}, {"date": "2012-09-20T20:00:00", "surprise": -0.56, "estimate": 0.53, "actual": 0.53}, {"date": "2012-06-18T21:00:00", "surprise": 4.7, "estimate": 0.78, "actual": 0.82}, {"date": "2012-03-20T20:00:00", "surprise": 10.36, "estimate": 0.56, "actual": 0.62}, {"date": "2011-12-20T21:00:00", "surprise": -5.31, "estimate": 0.57, "actual": 0.54}, {"date": "2011-09-20T20:00:00", "surprise": 3.13, "estimate": 0.47, "actual": 0.48}, {"date": "2011-06-23T20:00:00", "surprise": 5.04, "estimate": 0.71, "actual": 0.75}, {"date": "2011-03-24T19:00:00", "surprise": 9.08, "estimate": 0.5, "actual": 0.54}, {"date": "2010-12-16T21:00:00", "surprise": 27.53, "estimate": 0.29, "actual": 0.37}, {"date": "2010-09-16T20:00:00", "surprise": 34.3, "estimate": 0.2, "actual": 0.27}, {"date": "2010-06-24T20:00:00", "surprise": 11.6, "estimate": 0.54, "actual": 0.6}, {"date": "2010-03-25T20:00:00", "surprise": 1.39, "estimate": 0.37, "actual": 0.38}, {"date": "2009-12-17T21:00:00", "surprise": 8.91, "estimate": 0.36, "actual": 0.39}, {"date": "2009-09-16T20:00:00", "surprise": -0.28, "estimate": 0.3, "actual": 0.3}, {"date": "2009-06-23T20:00:00", "surprise": 3.73, "estimate": 0.44, "actual": 0.46}, {"date": "2009-03-18T20:00:00", "surprise": 10.35, "estimate": 0.32, "actual": 0.35}, {"date": "2008-12-18T21:00:00", "surprise": -0.41, "estimate": 0.34, "actual": 0.34}, {"date": "2008-09-18T20:00:00", "surprise": 8.53, "estimate": 0.27, "actual": 0.29}, {"date": "2008-06-25T20:00:00", "surprise": 6.3, "estimate": 0.44, "actual": 0.47}, {"date": "2008-03-26T20:00:00", "surprise": -0.12, "estimate": 0.3, "actual": 0.3}, {"date": "2007-12-19T21:00:00", "surprise": 15.27, "estimate": 0.27, "actual": 0.31}, {"date": "2007-09-20T20:00:00", "surprise": 4.41, "estimate": 0.21, "actual": 0.22}, {"date": "2007-06-26T20:00:00", "surprise": 6.8, "estimate": 0.35, "actual": 0.37}, {"date": "2007-03-20T20:00:00", "surprise": 11.61, "estimate": 0.22, "actual": 0.25}, {"date": "2006-12-18T21:00:00", "surprise": -0.7, "estimate": 0.22, "actual": 0.22}, {"date": "2006-09-19T20:00:00", "surprise": 10.82, "estimate": 0.16, "actual": 0.18}, {"date": "2006-06-22T20:00:00", "surprise": 2.69, "estimate": 0.28, "actual": 0.29}, {"date": "2006-03-20T21:00:00", "surprise": 5.2, "estimate": 0.18, "actual": 0.19}, {"date": "2005-12-15T21:00:00", "surprise": 0.07, "estimate": 0.19, "actual": 0.19}, {"date": "2005-09-22T21:00:00", "surprise": 0.21, "estimate": 0.14, "actual": 0.14}, {"date": "2005-06-29T11:00:00", "surprise": 11.2, "estimate": 0.23, "actual": 0.26}, {"date": "2005-03-22T21:00:00", "surprise": 6.44, "estimate": 0.15, "actual": 0.16}, {"date": "2004-12-13T11:00:00", "surprise": 19.1, "estimate": 0.13, "actual": 0.16}, {"date": "2004-09-14T20:00:00", "surprise": 9.51, "estimate": 0.09, "actual": 0.1}, {"date": "2004-06-15T20:00:00", "surprise": 5.96, "estimate": 0.18, "actual": 0.19}, {"date": "2004-03-11T21:00:00", "surprise": 0.82, "estimate": 0.12, "actual": 0.12}, {"date": "2003-12-15T21:00:00", "surprise": 9.51, "estimate": 0.11, "actual": 0.12}, {"date": "2003-09-12T11:00:00", "surprise": -2.39, "estimate": 0.08, "actual": 0.08}, {"date": "2003-06-12T20:00:00", "surprise": 14.81, "estimate": 0.14, "actual": 0.16}, {"date": "2003-03-18T21:00:00", "surprise": 10.99, "estimate": 0.1, "actual": 0.11}, {"date": "2002-12-18T21:00:00", "surprise": 20.0, "estimate": 0.08, "actual": 0.1}, {"date": "2002-09-17T20:00:00", "surprise": 15.98, "estimate": 0.08, "actual": 0.09}, {"date": "2002-09-17T20:00:00", "surprise": -1.38, "estimate": 0.07, "actual": 0.07}, {"date": "2002-06-18T20:00:00", "surprise": 5.4, "estimate": 0.14, "actual": 0.15}, {"date": "2002-06-18T20:00:00", "surprise": 18.76, "estimate": 0.12, "actual": 0.14}, {"date": "2002-03-14T21:00:00", "surprise": -0.37, "estimate": 0.1, "actual": 0.1}]