[{"date": "2026-02-19T12:00:00", "surprise": -14.22, "estimate": 0.98, "actual": 0.84}, {"date": "2025-10-23T11:00:00", "surprise": 0.66, "estimate": 3.37, "actual": 3.39}, {"date": "2025-07-24T11:00:00", "surprise": 0.33, "estimate": 5.15, "actual": 5.17}, {"date": "2025-04-24T11:00:00", "surprise": -4.1, "estimate": 1.48, "actual": 1.42}, {"date": "2025-02-20T12:00:00", "surprise": 8.53, "estimate": 0.89, "actual": 0.97}, {"date": "2024-10-24T11:00:00", "surprise": 2.76, "estimate": 3.17, "actual": 3.26}, {"date": "2024-07-25T11:00:00", "surprise": 1.68, "estimate": 4.9, "actual": 4.98}, {"date": "2024-04-25T11:00:00", "surprise": -4.03, "estimate": 1.93, "actual": 1.85}, {"date": "2024-02-22T12:00:00", "surprise": 2.14, "estimate": 1.27, "actual": 1.3}, {"date": "2023-10-19T11:00:00", "surprise": 1.84, "estimate": 3.44, "actual": 3.5}, {"date": "2023-07-20T11:00:00", "surprise": -3.69, "estimate": 6.12, "actual": 5.89}, {"date": "2023-04-20T11:00:00", "surprise": -22.83, "estimate": 3.19, "actual": 2.46}, {"date": "2023-02-16T12:00:00", "surprise": -9.67, "estimate": 1.98, "actual": 1.79}, {"date": "2022-10-20T11:00:00", "surprise": 3.65, "estimate": 4.59, "actual": 4.76}, {"date": "2022-07-21T11:00:00", "surprise": 2.66, "estimate": 7.39, "actual": 7.59}, {"date": "2022-04-21T11:00:00", "surprise": 36.7, "estimate": 3.09, "actual": 4.23}, {"date": "2022-02-17T12:00:00", "surprise": 18.65, "estimate": 1.92, "actual": 2.28}, {"date": "2021-10-21T11:00:00", "surprise": 13.64, "estimate": 3.87, "actual": 4.4}, {"date": "2021-07-22T11:00:00", "surprise": 12.55, "estimate": 5.49, "actual": 6.18}, {"date": "2021-04-22T11:00:00", "surprise": 50.0, "estimate": 1.16, "actual": 2.32}, {"date": "2021-02-11T12:00:00", "surprise": 50.0, "estimate": 0.8, "actual": 1.45}, {"date": "2020-10-22T11:00:00", "surprise": 23.84, "estimate": 2.19, "actual": 2.71}, {"date": "2020-07-23T11:00:00", "surprise": 18.1, "estimate": 3.15, "actual": 3.72}, {"date": "2020-04-23T12:00:00", "surprise": 11.71, "estimate": 0.64, "actual": 0.71}, {"date": "2020-02-13T12:00:00", "surprise": 20.36, "estimate": 0.37, "actual": 0.44}, {"date": "2019-10-17T11:00:00", "surprise": 9.32, "estimate": 1.78, "actual": 1.95}, {"date": "2019-07-18T11:00:00", "surprise": -0.16, "estimate": 3.23, "actual": 3.22}, {"date": "2019-04-18T11:00:00", "surprise": 25.0, "estimate": 0.64, "actual": 0.8}, {"date": "2019-02-14T12:00:00", "surprise": -7.08, "estimate": 0.44, "actual": 0.41}, {"date": "2018-10-18T11:00:00", "surprise": 4.57, "estimate": 1.59, "actual": 1.66}, {"date": "2018-07-19T11:00:00", "surprise": -2.78, "estimate": 2.88, "actual": 2.8}, {"date": "2018-04-19T11:00:00", "surprise": 6.38, "estimate": 0.71, "actual": 0.75}, {"date": "2018-02-15T12:00:00", "surprise": 23.53, "estimate": 0.17, "actual": 0.21}, {"date": "2017-10-19T11:00:00", "surprise": 0.35, "estimate": 1.16, "actual": 1.16}, {"date": "2017-07-20T11:00:00", "surprise": -1.43, "estimate": 2.24, "actual": 2.21}, {"date": "2017-04-20T11:00:00", "surprise": 30.65, "estimate": 0.4, "actual": 0.52}, {"date": "2016-10-20T11:00:00", "surprise": 2.88, "estimate": 1.01, "actual": 1.04}, {"date": "2016-07-21T11:00:00", "surprise": 2.72, "estimate": 1.93, "actual": 1.98}, {"date": "2016-04-21T11:00:00", "surprise": 50.0, "estimate": 0.24, "actual": 0.38}, {"date": "2016-02-18T12:00:00", "surprise": 50.0, "estimate": -0.01, "actual": 0.06}, {"date": "2015-10-22T11:00:00", "surprise": 2.86, "estimate": 0.88, "actual": 0.9}, {"date": "2015-07-23T11:00:00", "surprise": -1.89, "estimate": 1.78, "actual": 1.75}, {"date": "2015-04-23T11:00:00", "surprise": 40.0, "estimate": 0.14, "actual": 0.19}, {"date": "2015-02-12T12:00:00", "surprise": 31.38, "estimate": -0.07, "actual": -0.05}, {"date": "2014-10-16T11:00:00", "surprise": -0.21, "estimate": 0.78, "actual": 0.78}, {"date": "2014-07-17T11:00:00", "surprise": -0.1, "estimate": 1.61, "actual": 1.61}, {"date": "2014-04-17T11:00:00", "surprise": -12.9, "estimate": 0.1, "actual": 0.09}, {"date": "2014-02-13T12:00:00", "surprise": 4.93, "estimate": -0.12, "actual": -0.11}, {"date": "2013-10-17T11:00:00", "surprise": -5.34, "estimate": 0.72, "actual": 0.68}, {"date": "2013-07-18T11:00:00", "surprise": -1.7, "estimate": 1.41, "actual": 1.39}, {"date": "2013-04-18T11:00:00", "surprise": 36.2, "estimate": 0.05, "actual": 0.07}, {"date": "2013-02-14T12:00:00", "surprise": 10.53, "estimate": -0.19, "actual": -0.17}, {"date": "2012-10-18T11:00:00", "surprise": 4.42, "estimate": 0.56, "actual": 0.59}, {"date": "2012-07-19T11:00:00", "surprise": -0.74, "estimate": 1.35, "actual": 1.34}, {"date": "2012-04-19T11:00:00", "surprise": 50.0, "estimate": 0.02, "actual": 0.06}, {"date": "2012-02-16T12:00:00", "surprise": 11.77, "estimate": -0.22, "actual": -0.19}, {"date": "2011-10-20T14:00:00", "surprise": 3.69, "estimate": 0.48, "actual": 0.5}, {"date": "2011-07-21T11:00:00", "surprise": 3.08, "estimate": 1.15, "actual": 1.19}, {"date": "2011-04-21T11:00:00", "surprise": 50.0, "estimate": -0.07, "actual": -0.01}, {"date": "2011-02-17T12:00:00", "surprise": -2.72, "estimate": -0.23, "actual": -0.24}, {"date": "2010-10-21T11:00:00", "surprise": 7.84, "estimate": 0.42, "actual": 0.45}, {"date": "2010-07-22T11:00:00", "surprise": 1.07, "estimate": 1.04, "actual": 1.05}, {"date": "2010-04-22T10:00:00", "surprise": 18.92, "estimate": -0.15, "actual": -0.12}, {"date": "2010-02-18T13:00:00", "surprise": -10.66, "estimate": -0.24, "actual": -0.27}, {"date": "2009-10-27T12:00:00", "surprise": -15.87, "estimate": 0.42, "actual": 0.35}, {"date": "2009-07-23T12:00:00", "surprise": 10.99, "estimate": 0.89, "actual": 0.99}, {"date": "2009-04-23T12:00:00", "surprise": -22.23, "estimate": -0.11, "actual": -0.13}, {"date": "2009-02-19T13:00:00", "surprise": -17.87, "estimate": -0.26, "actual": -0.31}, {"date": "2008-10-23T12:00:00", "surprise": 3.13, "estimate": 0.44, "actual": 0.45}, {"date": "2008-07-24T12:00:00", "surprise": 1.7, "estimate": 1.07, "actual": 1.09}, {"date": "2008-04-24T12:00:00", "surprise": -26.24, "estimate": -0.06, "actual": -0.07}, {"date": "2008-02-21T13:00:00", "surprise": -50.0, "estimate": -0.13, "actual": -0.24}, {"date": "2007-10-23T12:00:00", "surprise": -6.89, "estimate": 0.46, "actual": 0.43}, {"date": "2007-07-19T12:00:00", "surprise": -0.27, "estimate": 1.12, "actual": 1.12}, {"date": "2007-04-19T12:00:00", "surprise": -8.33, "estimate": 0.07, "actual": 0.06}, {"date": "2007-02-15T13:00:00", "surprise": -11.11, "estimate": -0.09, "actual": -0.1}, {"date": "2006-07-20T12:00:00", "surprise": 1.27, "estimate": 1.11, "actual": 1.12}, {"date": "2006-04-20T12:00:00", "surprise": 12.15, "estimate": 0.11, "actual": 0.12}, {"date": "2005-10-20T12:00:00", "surprise": 1.66, "estimate": 0.48, "actual": 0.49}, {"date": "2005-07-21T12:00:00", "surprise": 3.1, "estimate": 0.9, "actual": 0.93}, {"date": "2005-04-21T12:00:00", "surprise": 2.86, "estimate": 0.09, "actual": 0.09}, {"date": "2005-02-17T13:00:00", "surprise": 19.35, "estimate": -0.06, "actual": -0.05}, {"date": "2004-10-21T11:00:00", "surprise": -0.17, "estimate": 0.39, "actual": 0.39}, {"date": "2004-07-22T12:00:00", "surprise": 0.17, "estimate": 0.77, "actual": 0.77}, {"date": "2004-04-22T12:00:00", "surprise": 50.0, "estimate": 0.03, "actual": 0.07}, {"date": "2004-02-19T13:00:00", "surprise": 25.93, "estimate": -0.07, "actual": -0.05}, {"date": "2003-10-22T12:00:00", "surprise": -17.14, "estimate": 0.39, "actual": 0.33}, {"date": "2003-07-24T12:00:00", "surprise": 1.76, "estimate": 0.6, "actual": 0.61}, {"date": "2003-04-24T13:00:00", "surprise": 15.36, "estimate": 0.02, "actual": 0.03}, {"date": "2003-02-13T14:00:00", "surprise": 8.27, "estimate": -0.05, "actual": -0.05}, {"date": "2002-10-15T13:00:00", "surprise": 3.63, "estimate": 0.24, "actual": 0.25}, {"date": "2002-07-16T11:00:00", "surprise": 50.0, "estimate": 0.42, "actual": 0.63}, {"date": "2002-07-16T11:00:00", "surprise": -0.91, "estimate": 0.49, "actual": 0.48}, {"date": "2002-04-16T12:00:00", "surprise": 40.18, "estimate": 0.02, "actual": 0.03}, {"date": "2002-04-16T12:00:00", "surprise": 50.0, "estimate": 0.01, "actual": 0.03}, {"date": "2002-02-07T13:00:00", "surprise": 28.57, "estimate": -0.09, "actual": -0.07}]